{"name":"MusicPlayer","tagline":"Music player - endlessly plays your music","body":"Music player\r\n============\r\n\r\n[Download latest MusicPlayer for MacOSX](https://github.com/downloads/albertz/music-player/MusicPlayer-latest.zip)\r\n\r\n![MusicPlayer screenshot](https://github.com/albertz/music-player/raw/master/screenshot.png)\r\n\r\nThis music player is supposed to be simple and all centered around an infinite intelligent queue (some other players call this PartyShuffle or DJ mode). You can manually add songs to it - but if you don't or the queue gets too short, it will automatically intelligently fill it with further songs.\r\n\r\nIf you wonder about what is supposed to be a music player or what makes a music player different from a simple media player, read this: [What is a music player](https://github.com/albertz/music-player/blob/master/WhatIsAMusicPlayer.md)\r\n\r\nThe code is highly modular. Most systems are optional. Also the GUI is an optional module. The music player can also run headless. Read more about [technical internals](https://github.com/albertz/music-player/blob/master/DevelopmentNotes.md).\r\n\r\nThe intelligent queue decision currently is based on:\r\n\r\n* song ratings\r\n* context-based choices, e.g. related songs more likely\r\n\r\nOther features of this player:\r\n\r\n* open source, simplified BSD license\r\n* simple\r\n* support of most important sound formats. just uses FFmpeg\r\n* simple music database\r\n* audio volume normalization. own ReplayGain implementation\r\n* [gapless playback](http://en.wikipedia.org/wiki/Gapless_playback)\r\n* Last.fm scrobbling\r\n* AcoustID fingerprint / MusicBrainz integration\r\n* imports iTunes song ratings\r\n\r\nAnnoyed by all existing players because some subset of:\r\n\r\n* not open source\r\n* missing sound format ([FLAC](http://flac.sourceforge.net/itunes.html), Ogg, ...)\r\n* bugs ([1](http://bugzilla.songbirdnest.com/show_bug.cgi?id=23640), [2](http://bugzilla.songbirdnest.com/show_bug.cgi?id=25023), [3](http://bugzilla.songbirdnest.com/show_bug.cgi?id=25042), [4](http://bugzilla.songbirdnest.com/show_bug.cgi?id=18503), [5](http://bugzilla.songbirdnest.com/show_bug.cgi?id=18505), [6](http://bugzilla.songbirdnest.com/show_bug.cgi?id=18480), [7](http://bugzilla.songbirdnest.com/show_bug.cgi?id=18478), [8](http://bugzilla.songbirdnest.com/show_bug.cgi?id=25073), [9](http://bugzilla.songbirdnest.com/show_bug.cgi?id=25024), [10](http://bugzilla.songbirdnest.com/show_bug.cgi?id=5975), ...)\r\n* missing output possibility (RAOP, PulseAudio, ...)\r\n* no or too limited DJ mode\r\n* no library / database\r\n* not running well on my platform of choice\r\n\r\nTODO / possible additional missing features:\r\n\r\n* BPM determination and clever DJ-like fading\r\n* use tags given by Last.fm (mostly more tags)\r\n* watch music directory for changes (e.g. new files added)\r\n* PyQt GUI interface\r\n\r\nThe current GUI is Cocoa only. Additional Qt support is planned. The music player also works without any GUI.","google":"","note":"Don't delete this file! It's used internally to help with page regeneration."}